cycles/__init__.py
cycles/cycles.py
cycles/cycles_input.py
cycles/cycles_read.py
cycles/cycles_runner.py
cycles/cycles_tools.py
cycles/planting_dates.py
cycles/data/GLDASp5_elevation_025d.nc4
cycles/data/GLDASp5_landmask_025d.nc4
cycles/data/NLDAS_elevation.nc4
cycles/data/NLDAS_masks-veg-soil.nc4
cycles/data/fips_gid_conversion.csv
cycles/data/gridMET_elevation_mask.nc
cycles/data/metdata_elevationdata.nc
cycles/data/us_states.csv
cycles/gadm/__init__.py
cycles/gadm/gadm.py
cycles/gssurgo/__init__.py
cycles/gssurgo/gssurgo.py
cycles/plot/__init__.py
cycles/plot/plot.py
cycles/soilgrids/__init__.py
cycles/soilgrids/soilgrids.py
cycles/weather/__init__.py
cycles/weather/weather.py
cycles_utils-3.1.0.dist-info/licenses/LICENSE
cycles_utils-3.1.0.dist-info/METADATA
cycles_utils-3.1.0.dist-info/WHEEL
cycles_utils-3.1.0.dist-info/top_level.txt
cycles_utils-3.1.0.dist-info/RECORD
